ltplugins/__about__.py
ltplugins/__init__.py
ltplugins/ltplugins.py
ltplugins-1.1.5.dist-info/LICENSE
ltplugins-1.1.5.dist-info/METADATA
ltplugins-1.1.5.dist-info/WHEEL
ltplugins-1.1.5.dist-info/top_level.txt
ltplugins-1.1.5.dist-info/RECORD
