Metadata-Version: 2.1
Name: ltplugins
Version: 1.1.5
Summary: Lite plugins for simple Python 3 projects
Home-page: https://github.com/mezantrop/ltplugins
Author: Mikhail Zakharov
Author-email: zmey20000@yahoo.com
License: bsd-2-clause
Keywords: plugin,modules
Platform: UNKNOWN
Classifier: License :: OSI Approved :: BSD License
Classifier: Development Status :: 5 - Production/Stable
Classifier: Intended Audience :: Developers
Classifier: Intended Audience :: Information Technology
Classifier: Operating System :: OS Independent
Classifier: Programming Language :: Python :: 3
Classifier: Topic :: Software Development
Classifier: Topic :: Software Development :: Libraries
Classifier: Topic :: Software Development :: Libraries :: Python Modules
